seeed_python_ircamera.py
seeed_python_ircamera-1.9.3.dist-info/LICENSE
seeed_python_ircamera-1.9.3.dist-info/METADATA
seeed_python_ircamera-1.9.3.dist-info/WHEEL
seeed_python_ircamera-1.9.3.dist-info/entry_points.txt
seeed_python_ircamera-1.9.3.dist-info/top_level.txt
seeed_python_ircamera-1.9.3.dist-info/RECORD
