Metadata-Version: 2.1
Name: seeed-python-ircamera
Version: 1.9.3
Summary: 32 x 24 pixels IRCamera Application
Home-page: https://github.com/gobuyun/seeed_ircamera
Author: gobuyun
Author-email: 874751353@qq.com
License: MIT
Keywords: seeed 32x24 IR sensor Application
Platform: UNKNOWN
Classifier: Development Status :: 3 - Alpha
Classifier: Intended Audience :: Developers
Classifier: Topic :: Software Development :: Libraries
Classifier: Topic :: System :: Hardware
Classifier: License :: OSI Approved :: MIT License
Classifier: Programming Language :: Python :: 3
Classifier: Programming Language :: Python :: 3.4
Classifier: Programming Language :: Python :: 3.5
Classifier: Programming Language :: Python :: 3.6
Classifier: Programming Language :: Python :: 3.7
Requires-Dist: pyserial
Requires-Dist: seeed-python-mlx9064x
